{
    "keep": {
        "days": true,
        "amount": 60
    },
    "auditLog": "E:\\busit_project\\busit_nodejs\\logs\\.84257f1b9fc60934e44b1fb526b5d3f87d7ee481-audit.json",
    "files": [
        {
            "date": 1754480820186,
            "name": "E:\\busit_project\\busit_nodejs\\logs\\access-2025-08-06.log",
            "hash": "bb001ce9fa0ddfb02b4aaf70b1687d23ccdd652d076481f44d7ee3cf69fb9944"
        },
        {
            "date": 1754845344277,
            "name": "E:\\busit_project\\busit_nodejs\\logs\\access-2025-08-11.log",
            "hash": "fcbbf797cb7e097f6af72a65a369122f376dce996b9bf275d3ab05f8efd994f5"
        }
    ],
    "hashType": "sha256"
}